CHANGELOG.txt
LICENSE.txt
MANIFEST.in
README.txt
setup.py
test_esales.py
esales/__init__.py
esales.egg-info/PKG-INFO
esales.egg-info/SOURCES.txt
esales.egg-info/dependency_links.txt
esales.egg-info/top_level.txt