Metadata-Version: 2.1
Name: esales
Version: 0.0.7
Summary: This is a very simple eslaes module :)
Home-page: UNKNOWN
Author: Rients Hoeksma
Author-email: rientshoeksma@gmail.com
License: MIT
Keywords: esales
Platform: UNKNOWN
Classifier: Development Status :: 5 - Production/Stable
Classifier: Intended Audience :: Education
Classifier: Operating System :: Microsoft :: Windows :: Windows 10
Classifier: License :: OSI Approved :: MIT License
Classifier: Programming Language :: Python :: 3
